excel_solver.py
excel_solver-0.0.0.dist-info/METADATA
excel_solver-0.0.0.dist-info/WHEEL
excel_solver-0.0.0.dist-info/licenses/LICENSE
excel_solver-0.0.0.dist-info/RECORD
