Metadata-Version: 2.1
Name: excel-solver
Version: 0.0.0
Project-URL: Documentation, https://github.com/ryayoung/py-excel-solver
Project-URL: Source Code, https://github.com/ryayoung/py-excel-solver
Author-email: Ryan Young <dev@ryayoung.com>
Maintainer-email: Ryan Young <dev@ryayoung.com>
License: Copyright (C) 2022 Ryan Young
License-File: LICENSE
Keywords: 
Classifier: Environment :: Console
Classifier: Intended Audience :: Science/Research
Classifier: License :: OSI Approved :: MIT License
Classifier: Operating System :: OS Independent
Classifier: Programming Language :: Python :: 3.10
Classifier: Topic :: Scientific/Engineering
Requires-Python: >=3.10
Requires-Dist: scipy
